flask_sockets.py
Flask_Sockets_Skeh-0.2.2.dist-info/LICENSE
Flask_Sockets_Skeh-0.2.2.dist-info/METADATA
Flask_Sockets_Skeh-0.2.2.dist-info/WHEEL
Flask_Sockets_Skeh-0.2.2.dist-info/top_level.txt
Flask_Sockets_Skeh-0.2.2.dist-info/RECORD
